fairseq_ext/__init__.py
fairseq_ext/average_checkpoints.py
fairseq_ext/binarize.py
fairseq_ext/generate.py
fairseq_ext/generate_sliding.py
fairseq_ext/options.py
fairseq_ext/options_train.py
fairseq_ext/preprocess.py
fairseq_ext/preprocess_bart.py
fairseq_ext/preprocess_bartsv.py
fairseq_ext/preprocess_graphmp.py
fairseq_ext/sequence_generator.py
fairseq_ext/sequence_generator_bartsv.py
fairseq_ext/sequence_generator_graph.py
fairseq_ext/sequence_generator_graphmp.py
fairseq_ext/tokenizer.py
fairseq_ext/train.py
fairseq_ext/utils.py
fairseq_ext/utils_font.py
fairseq_ext/utils_import.py
fairseq_ext/amr_reform/__init__.py
fairseq_ext/amr_reform/o10_action_reformer_subtok.py
fairseq_ext/amr_spec/__init__.py
fairseq_ext/amr_spec/action_info.py
fairseq_ext/amr_spec/action_info_bartsv.py
fairseq_ext/amr_spec/action_info_binarize.py
fairseq_ext/amr_spec/action_info_binarize_bartsv.py
fairseq_ext/amr_spec/action_info_binarize_graphmp.py
fairseq_ext/amr_spec/action_info_binarize_graphmp_amr1.py
fairseq_ext/amr_spec/action_info_graphmp.py
fairseq_ext/amr_spec/action_info_graphmp_amr1.py
fairseq_ext/amr_spec/old_action_info.py
fairseq_ext/amr_spec/old_action_info_binarize.py
fairseq_ext/criterions/__init__.py
fairseq_ext/criterions/label_smoothed_cross_entropy_pointer.py
fairseq_ext/criterions/label_smoothed_cross_entropy_pointer_alignment.py
fairseq_ext/data/__init__.py
fairseq_ext/data/amr_action_pointer_bartsv_dataset.py
fairseq_ext/data/amr_action_pointer_dataset.py
fairseq_ext/data/amr_action_pointer_goldamr_dataset.py
fairseq_ext/data/amr_action_pointer_graphmp_dataset.py
fairseq_ext/data/amr_bpe.py
fairseq_ext/data/data_utils.py
fairseq_ext/data/indexed_dataset.py
fairseq_ext/data/language_pair_dataset.py
fairseq_ext/extract_bart/__init__.py
fairseq_ext/extract_bart/binarize_encodings.py
fairseq_ext/extract_bart/composite_embeddings.py
fairseq_ext/extract_bart/mapavg_embeddings.py
fairseq_ext/extract_bart/sentence_encoding.py
fairseq_ext/models/__init__.py
transition_neural_parser-0.5.1002.dist-info/LICENSE
transition_neural_parser-0.5.1002.dist-info/METADATA
transition_neural_parser-0.5.1002.dist-info/WHEEL
transition_neural_parser-0.5.1002.dist-info/entry_points.txt
transition_neural_parser-0.5.1002.dist-info/top_level.txt
transition_neural_parser-0.5.1002.dist-info/RECORD
