Metadata-Version: 2.1
Name: transition-neural-parser
Version: 0.5.1002
Summary: A small example package
Author-email: GX <GX.Xu@ibm.com>
Project-URL: Homepage, https://github.ibm.com/mnlp/transition-amr-parser/tree/transition-neural-parser
Project-URL: Bug Tracker, https://github.ibm.com/mnlp/transition-amr-parser/issues
Classifier: Programming Language :: Python :: 3
Classifier: License :: OSI Approved :: Apache Software License
Classifier: Operating System :: OS Independent
Requires-Python: >=3.7
License-File: LICENSE
Requires-Dist: torch (==1.13.1)
Requires-Dist: numpy (<=1.23.5)
Requires-Dist: tqdm (>=4.55.0)
Requires-Dist: fairseq (==0.10.2)
Requires-Dist: packaging (>=20.8)
Requires-Dist: requests (>=2.25.1)
Requires-Dist: h5py (>=3.0.0)
Requires-Dist: python-dateutil (>=2.8.1)
Requires-Dist: penman (>=1.1.0)
Requires-Dist: smatch (>=1.0.3.2)
Requires-Dist: ipdb (>=0.13.0)
Requires-Dist: line-profiler (>=4.0.2)
Requires-Dist: pyinstrument (>=4.4.0)
Requires-Dist: boto3 (>=1.26.1)
Requires-Dist: progressbar
